redfin_scraper/__init__.py
redfin_scraper/config.py
redfin_scraper/core/__init__.py
redfin_scraper/core/redfin_scraper.py
redfin_scraper/resources/__init__.py
redfin_scraper/resources/json_tools.py
redfin_scraper/resources/logging.py
redfin_scraper-0.2.2.dist-info/LICENSE.txt
redfin_scraper-0.2.2.dist-info/METADATA
redfin_scraper-0.2.2.dist-info/WHEEL
redfin_scraper-0.2.2.dist-info/top_level.txt
redfin_scraper-0.2.2.dist-info/RECORD
