Metadata-Version: 2.1
Name: redfin-scraper
Version: 0.2.2
Summary: A Python library used to scrape data from Redfin.com using the unofficial Stringray API.
Author-email: Ryan Sherby <ryan.m.sherby@gmail.com>
License: MIT License
Project-URL: Homepage, https://github.com/ryansherby/RedfinScraper
Keywords: scraper,scraping,Redfin,real estate,data,housing,houses
Classifier: License :: OSI Approved :: MIT License
Classifier: Programming Language :: Python
Classifier: Programming Language :: Python :: 3
Requires-Python: >=3.9
Provides-Extra: dev
License-File: LICENSE.txt
